cloudmesh_iu-4.1.2-py3.8-nspkg.pth
cloudmesh/iu/__init__.py
cloudmesh/iu/__version__.py
cloudmesh/iu/command/__init__.py
cloudmesh/iu/command/iu.py
cloudmesh/iu/system/__init__.py
cloudmesh/iu/system/manager.py
cloudmesh_iu-4.1.2.dist-info/LICENSE
cloudmesh_iu-4.1.2.dist-info/METADATA
cloudmesh_iu-4.1.2.dist-info/WHEEL
cloudmesh_iu-4.1.2.dist-info/namespace_packages.txt
cloudmesh_iu-4.1.2.dist-info/top_level.txt
cloudmesh_iu-4.1.2.dist-info/RECORD
