Metadata-Version: 2.1
Name: cloudmesh-iu
Version: 4.1.2
Summary: A command called iu and foo for the cloudmesh shell
Home-page: https://github.com/cloudmesh/cloudmesh-iu
Author: Gregor von Laszewski
Author-email: laszewski@gmail.com
License: Apache 2.0
Platform: UNKNOWN
Classifier: Development Status :: 5 - Production/Stable
Classifier: Environment :: Web Environment
Classifier: Intended Audience :: Developers
Classifier: License :: OSI Approved :: BSD License
Classifier: Operating System :: OS Independent
Classifier: Programming Language :: Python
Classifier: Programming Language :: Python :: 3
Classifier: Programming Language :: Python :: 3.7
Classifier: Programming Language :: Python :: 3.8
Requires-Dist: cloudmesh-configuration
Requires-Dist: cloudmesh-cmd5
Requires-Dist: cloudmesh-gui
